pydra/tasks/petpvc/__init__.py
pydra/tasks/petpvc/petpvc.py
pydra/tasks/petpvc/specs.py
pydra/tasks/petpvc/utils.py
clinica_pydra_petpvc-0.1.0.dist-info/METADATA
clinica_pydra_petpvc-0.1.0.dist-info/WHEEL
clinica_pydra_petpvc-0.1.0.dist-info/licenses/LICENSE
clinica_pydra_petpvc-0.1.0.dist-info/RECORD
