Metadata-Version: 2.3
Name: clinica-pydra-petpvc
Version: 0.1.0
Summary: Pydra tasks for PETPVC designed for Clinica
Project-URL: Documentation, https://github.com/ghisvail/clinica-pydra-petpvc#readme
Project-URL: Issues, https://github.com/ghisvail/clinica-pydra-petpvc/issues
Project-URL: Source, https://github.com/ghisvail/clinica-pydra-petpvc
Author-email: Ghislain Vaillant <ghislain.vaillant@inria.fr>
License-Expression: Apache-2.0
License-File: LICENSE
Keywords: pet,petpvc,pvc,pydra
Classifier: Development Status :: 3 - Alpha
Classifier: Intended Audience :: Science/Research
Classifier: License :: OSI Approved :: Apache Software License
Classifier: Operating System :: OS Independent
Classifier: Programming Language :: Python
Classifier: Programming Language :: Python :: 3.8
Classifier: Programming Language :: Python :: 3.9
Classifier: Programming Language :: Python :: 3.10
Classifier: Programming Language :: Python :: 3.11
Classifier: Programming Language :: Python :: 3.12
Classifier: Topic :: Scientific/Engineering
Classifier: Topic :: Software Development :: Libraries
Requires-Python: >=3.8
Requires-Dist: attrs>=22.1
Requires-Dist: pydra>=0.22
